hclib/__init__.py
hclib/hashchecker.py
hclib/help_strings.py
hclib/core/__init__.py
hclib/core/core_actions.py
hclib/core/core_objects.py
hclib/core/exceptions.py
hclib/core/utils.py
tests/__init__.py
tests/core/__init__.py
tests/core/test_core_actions.py
tests/core/test_core_objects.py
hashchecker-1.3.dist-info/LICENCE
hashchecker-1.3.dist-info/METADATA
hashchecker-1.3.dist-info/WHEEL
hashchecker-1.3.dist-info/entry_points.txt
hashchecker-1.3.dist-info/top_level.txt
hashchecker-1.3.dist-info/RECORD
