Metadata-Version: 2.1
Name: hashchecker
Version: 1.3
Summary: A clean way to verify integrity of files.
Home-page: https://github.com/advaithhl/Hashchecker
Author: Advaith H L
Author-email: niceadvaith@gmail.com
License: GPLv3
Platform: UNKNOWN
Classifier: Programming Language :: Python :: 3
Classifier: License :: OSI Approved :: GNU General Public License v3 (GPLv3)
Requires-Dist: click (>=7.0)
Requires-Dist: colorama (>=0.4.1)
Requires-Dist: tabulate (>=0.8.3)
